dredger.py
dredger-0.1.0.dist-info/METADATA
dredger-0.1.0.dist-info/WHEEL
dredger-0.1.0.dist-info/top_level.txt
dredger-0.1.0.dist-info/RECORD
