Metadata-Version: 2.1
Name: dredger
Version: 0.1.0
Summary: This module is used to download uspto patent applications and grant files. It also has usefull datetime functions
Author-email: Ketan Chandra <ketan@incubig.org>
Project-URL: Homepage, https://github.com/IncubigInnovations/mining/dredger
Project-URL: Bug Tracker, https://github.com/IncubigInnovations/mining/issues
Classifier: Programming Language :: Python :: 3
Classifier: License :: OSI Approved :: MIT License
Classifier: Operating System :: OS Independent
Requires-Python: >=3.6
